{
  "main": {
    "id": "b7c69e7927efb2aa",
    "type": "split",
    "children": [
      {
        "id": "217536484a803b4b",
        "type": "tabs",
        "children": [
          {
            "id": "3f3f3be52713a039",
            "type": "leaf",
            "state": {
              "type": "markdown",
              "state": {
                "file": "声明.md",
                "mode": "preview",
                "source": false
              },
              "icon": "lucide-file",
              "title": "声明"
            }
          }
        ]
      }
    ],
    "direction": "vertical"
  },
  "left": {
    "id": "dd300ea5ffd84a78",
    "type": "split",
    "children": [
      {
        "id": "816d0f86c7e1dc48",
        "type": "tabs",
        "children": [
          {
            "id": "a37421e0619c3c1b",
            "type": "leaf",
            "state": {
              "type": "file-explorer",
              "state": {
                "sortOrder": "alphabetical",
                "autoReveal": false
              },
              "icon": "lucide-folder-closed",
              "title": "文件列表"
            }
          },
          {
            "id": "cd97e1776daac304",
            "type": "leaf",
            "state": {
              "type": "search",
              "state": {
                "query": "",
                "matchingCase": false,
                "explainSearch": false,
                "collapseAll": false,
                "extraContext": false,
                "sortOrder": "alphabetical"
              },
              "icon": "lucide-search",
              "title": "搜索"
            }
          },
          {
            "id": "325d33996aa66599",
            "type": "leaf",
            "state": {
              "type": "bookmarks",
              "state": {},
              "icon": "lucide-bookmark",
              "title": "书签"
            }
          }
        ]
      }
    ],
    "direction": "horizontal",
    "width": 300
  },
  "right": {
    "id": "19b0e8b553156668",
    "type": "split",
    "children": [
      {
        "id": "333c33d522e14e67",
        "type": "tabs",
        "children": [
          {
            "id": "0314dcd362b27532",
            "type": "leaf",
            "state": {
              "type": "backlink",
              "state": {
                "file": "银杏末叶/人物介绍/见末叶.md",
                "collapseAll": false,
                "extraContext": false,
                "sortOrder": "alphabetical",
                "showSearch": false,
                "searchQuery": "",
                "backlinkCollapsed": false,
                "unlinkedCollapsed": true
              },
              "icon": "links-coming-in",
              "title": "见末叶 的反向链接列表"
            }
          },
          {
            "id": "76d5cd1cc83d6b81",
            "type": "leaf",
            "state": {
              "type": "outgoing-link",
              "state": {
                "file": "银杏末叶/人物介绍/见末叶.md",
                "linksCollapsed": false,
                "unlinkedCollapsed": true
              },
              "icon": "links-going-out",
              "title": "见末叶 的出链列表"
            }
          },
          {
            "id": "0de5b95ebaa0b5e4",
            "type": "leaf",
            "state": {
              "type": "tag",
              "state": {
                "sortOrder": "frequency",
                "useHierarchy": true
              },
              "icon": "lucide-tags",
              "title": "标签"
            }
          },
          {
            "id": "9c53889038193aee",
            "type": "leaf",
            "state": {
              "type": "outline",
              "state": {
                "file": "欢迎.md"
              },
              "icon": "lucide-list",
              "title": "欢迎 的大纲"
            }
          }
        ]
      }
    ],
    "direction": "horizontal",
    "width": 300,
    "collapsed": true
  },
  "left-ribbon": {
    "hiddenItems": {
      "switcher:打开快速切换": false,
      "graph:查看关系图谱": false,
      "canvas:新建白板": false,
      "daily-notes:打开/创建今天的日记": false,
      "templates:插入模板": false,
      "command-palette:打开命令面板": false
    }
  },
  "active": "3f3f3be52713a039",
  "lastOpenFiles": [
    "银杏末叶/附件/「洪流相对扩增计划」.md",
    "银杏末叶/附件/「频道交流」.md",
    "银杏末叶/附件/「两年相对数据采集」.md",
    "人物介绍/本土角色/编号/015.png",
    "声明.md",
    "银杏末叶/正文/序 开始了？结束吧！.md",
    "银杏末叶/正文/第一章 见末叶先生.md",
    "银杏末叶/正文/第三章 青晨.md",
    "银杏末叶/正文/第二章 洪流.md",
    "银杏末叶/正文/第五章 缇姨.md",
    "银杏末叶/正文/第六章 尘灵.md",
    "银杏末叶/正文/第四章 世界树.md",
    "银杏末叶/附件/标准时间.md",
    "银杏末叶/附件/世界树科技/世界树科技.md",
    "银杏末叶/附件/世界树科技/空间拉伸.md",
    "银杏末叶/附件/世界树科技/空间拉伸间隙.md",
    "五代青史/简介.md",
    "荣蓉潭谈/第一章 将近一月的努力成果 —— 部分一：准备.md",
    "荣蓉潭谈/第一章 将近一月的努力成果 —— 部分二.md",
    "荣蓉潭谈/第二章 时隔半年的忽忆接续.md",
    "人物介绍/外来角色/桔子.md",
    "人物介绍/本土角色/非编号/依伊.md",
    "人物介绍/本土角色/非编号/依璃伊.md",
    "人物介绍/本土角色/非编号/外麻.md",
    "人物介绍/本土角色/非编号/戋幕.md",
    "人物介绍/本土角色/非编号/璃伊.md",
    "番外",
    "银杏末叶/附件/世界树科技",
    "贺焉原间",
    "地点介绍/幕间",
    "地点介绍/少间",
    "地点介绍/原间",
    "地点介绍/入间",
    "地点介绍/此间",
    "人物介绍/本土角色/非编号",
    "人物介绍/本土角色/编号"
  ]
}